topsis_harith_102303243/__init__.py
topsis_harith_102303243/cli.py
topsis_harith_102303243/topsis.py
topsis_harith_102303243-1.0.0.dist-info/licenses/LICENSE
topsis_harith_102303243-1.0.0.dist-info/METADATA
topsis_harith_102303243-1.0.0.dist-info/WHEEL
topsis_harith_102303243-1.0.0.dist-info/entry_points.txt
topsis_harith_102303243-1.0.0.dist-info/top_level.txt
topsis_harith_102303243-1.0.0.dist-info/RECORD
