Metadata-Version: 2.4
Name: Topsis-Harith-102303243
Version: 1.0.0
Summary: A Python package to implement TOPSIS ranking method.
Author-email: Harith <harith.khanna18@gmail.com>
License: MIT
Requires-Python: >=3.8
License-File: LICENSE
Requires-Dist: numpy
Requires-Dist: pandas
Dynamic: license-file
